{
    "type": "minecraft:crafting_shapeless",
    "ingredients": [
        "slabsandstairs:packed_ice_stairs",
        "slabsandstairs:packed_ice_stairs",
        "slabsandstairs:packed_ice_stairs",
        "slabsandstairs:packed_ice_stairs",
        "slabsandstairs:packed_ice_stairs",
        "slabsandstairs:packed_ice_stairs",
        "slabsandstairs:packed_ice_stairs",
        "slabsandstairs:packed_ice_stairs",
        "slabsandstairs:packed_ice_stairs"
    ],
    "result": {
        "count": 1,
        "id": "slabsandstairs:blue_ice_stairs"
    }
}