{
    "type": "minecraft:crafting_shapeless",
    "ingredients": [
        "slabsandstairs:yellow_concrete_layer",
        "slabsandstairs:yellow_concrete_layer",
        "slabsandstairs:yellow_concrete_layer",
        "slabsandstairs:yellow_concrete_layer",
        "slabsandstairs:yellow_concrete_layer",
        "slabsandstairs:yellow_concrete_layer",
        "slabsandstairs:yellow_concrete_layer",
        "slabsandstairs:yellow_concrete_layer"
    ],
    "result": {
        "count": 1,
        "id": "minecraft:yellow_concrete"
    }
}